Classfile /home/phagio/git/ASMASP/bin/com/laneve/asp/ASMAnalysis/tests/Tests.class
  Last modified Aug 1, 2016; size 1041 bytes
  MD5 checksum 858bbcd98afd225a9d593bbf365bd14f
  Compiled from "Tests.java"
public class com.laneve.asp.ASMAnalysis.tests.Tests
  SourceFile: "Tests.java"
  minor version: 0
  major version: 51
  flags: ACC_PUBLIC, ACC_SUPER
Constant pool:
   #1 = Class              #2             //  com/laneve/asp/ASMAnalysis/tests/Tests
   #2 = Utf8               com/laneve/asp/ASMAnalysis/tests/Tests
   #3 = Class              #4             //  java/lang/Object
   #4 = Utf8               java/lang/Object
   #5 = Utf8               <init>
   #6 = Utf8               ()V
   #7 = Utf8               Code
   #8 = Methodref          #3.#9          //  java/lang/Object."<init>":()V
   #9 = NameAndType        #5:#6          //  "<init>":()V
  #10 = Utf8               LineNumberTable
  #11 = Utf8               LocalVariableTable
  #12 = Utf8               this
  #13 = Utf8               Lcom/laneve/asp/ASMAnalysis/tests/Tests;
  #14 = Utf8               foo
  #15 = Utf8               (I)I
  #16 = Methodref          #1.#17         //  com/laneve/asp/ASMAnalysis/tests/Tests.bar:(I)I
  #17 = NameAndType        #18:#15        //  bar:(I)I
  #18 = Utf8               bar
  #19 = Utf8               a
  #20 = Utf8               I
  #21 = Utf8               release
  #22 = Utf8               (Ljava/lang/Thread;I)V
  #23 = Utf8               Exceptions
  #24 = Class              #25            //  java/lang/InterruptedException
  #25 = Utf8               java/lang/InterruptedException
  #26 = Methodref          #27.#29        //  java/lang/Thread.join:()V
  #27 = Class              #28            //  java/lang/Thread
  #28 = Utf8               java/lang/Thread
  #29 = NameAndType        #30:#6         //  join:()V
  #30 = Utf8               join
  #31 = Utf8               t
  #32 = Utf8               Ljava/lang/Thread;
  #33 = Utf8               i
  #34 = Methodref          #27.#9         //  java/lang/Thread."<init>":()V
  #35 = Methodref          #27.#36        //  java/lang/Thread.run:()V
  #36 = NameAndType        #37:#6         //  run:()V
  #37 = Utf8               run
  #38 = Utf8               x
  #39 = Utf8               ()I
  #40 = Utf8               t5
  #41 = Utf8               main
  #42 = Methodref          #1.#9          //  com/laneve/asp/ASMAnalysis/tests/Tests."<init>":()V
  #43 = Methodref          #1.#44         //  com/laneve/asp/ASMAnalysis/tests/Tests.release:(Ljava/lang/Thread;I)V
  #44 = NameAndType        #21:#22        //  release:(Ljava/lang/Thread;I)V
  #45 = Utf8               SourceFile
  #46 = Utf8               Tests.java
{
  public com.laneve.asp.ASMAnalysis.tests.Tests();
    flags: ACC_PUBLIC
    Code:
      stack=1, locals=1, args_size=1
         0: aload_0       
         1: invokespecial #8                  // Method java/lang/Object."<init>":()V
         4: return        
      LineNumberTable:
        line 3: 0
      LocalVariableTable:
        Start  Length  Slot  Name   Signature
               0       5     0  this   Lcom/laneve/asp/ASMAnalysis/tests/Tests;

  public int foo(int);
    flags: ACC_PUBLIC
    Code:
      stack=3, locals=2, args_size=2
         0: iload_1       
         1: aload_0       
         2: iload_1       
         3: invokevirtual #16                 // Method bar:(I)I
         6: imul          
         7: ireturn       
      LineNumberTable:
        line 6: 0
      LocalVariableTable:
        Start  Length  Slot  Name   Signature
               0       8     0  this   Lcom/laneve/asp/ASMAnalysis/tests/Tests;
               0       8     1     a   I

  public void release(java.lang.Thread, int) throws java.lang.InterruptedException;
    flags: ACC_PUBLIC
    Exceptions:
      throws java.lang.InterruptedException
    Code:
      stack=1, locals=3, args_size=3
         0: aload_1       
         1: invokevirtual #26                 // Method java/lang/Thread.join:()V
         4: return        
      LineNumberTable:
        line 10: 0
        line 11: 4
      LocalVariableTable:
        Start  Length  Slot  Name   Signature
               0       5     0  this   Lcom/laneve/asp/ASMAnalysis/tests/Tests;
               0       5     1     t   Ljava/lang/Thread;
               0       5     2     i   I

  public int bar(int);
    flags: ACC_PUBLIC
    Code:
      stack=3, locals=4, args_size=2
         0: new           #27                 // class java/lang/Thread
         3: dup           
         4: invokespecial #34                 // Method java/lang/Thread."<init>":()V
         7: astore_2      
         8: aload_2       
         9: invokevirtual #35                 // Method java/lang/Thread.run:()V
        12: iload_1       
        13: iload_1       
        14: iconst_3      
        15: iadd          
        16: imul          
        17: istore_3      
        18: iload_3       
        19: ireturn       
      LineNumberTable:
        line 15: 0
        line 16: 8
        line 17: 12
        line 19: 18
      LocalVariableTable:
        Start  Length  Slot  Name   Signature
               0      20     0  this   Lcom/laneve/asp/ASMAnalysis/tests/Tests;
               0      20     1     a   I
               8      12     2     t   Ljava/lang/Thread;
              18       2     3     x   I

  public int bar() throws java.lang.InterruptedException;
    flags: ACC_PUBLIC
    Exceptions:
      throws java.lang.InterruptedException
    Code:
      stack=2, locals=2, args_size=1
         0: new           #27                 // class java/lang/Thread
         3: dup           
         4: invokespecial #34                 // Method java/lang/Thread."<init>":()V
         7: astore_1      
         8: aload_1       
         9: invokevirtual #35                 // Method java/lang/Thread.run:()V
        12: aload_1       
        13: invokevirtual #26                 // Method java/lang/Thread.join:()V
        16: iconst_2      
        17: ireturn       
      LineNumberTable:
        line 24: 0
        line 26: 8
        line 27: 12
        line 29: 16
      LocalVariableTable:
        Start  Length  Slot  Name   Signature
               0      18     0  this   Lcom/laneve/asp/ASMAnalysis/tests/Tests;
               8      10     1    t5   Ljava/lang/Thread;

  public static void main() throws java.lang.InterruptedException;
    flags: ACC_PUBLIC, ACC_STATIC
    Exceptions:
      throws java.lang.InterruptedException
    Code:
      stack=3, locals=1, args_size=0
         0: new           #1                  // class com/laneve/asp/ASMAnalysis/tests/Tests
         3: dup           
         4: invokespecial #42                 // Method "<init>":()V
         7: astore_0      
         8: aload_0       
         9: new           #27                 // class java/lang/Thread
        12: dup           
        13: invokespecial #34                 // Method java/lang/Thread."<init>":()V
        16: iconst_0      
        17: invokevirtual #43                 // Method release:(Ljava/lang/Thread;I)V
        20: return        
      LineNumberTable:
        line 34: 0
        line 55: 8
        line 58: 20
      LocalVariableTable:
        Start  Length  Slot  Name   Signature
               8      13     0     x   Lcom/laneve/asp/ASMAnalysis/tests/Tests;
}
